{
    "data": {
        "data_directory": ["./data/"],
        "data_name": ["data_resource_usage_5Minutes_6176858948"
                      ],
        "features": [[["meanCPUUsage"], ["meanCPUUsage"]]]
    },
    
    "encoder_decoder": {
        "activation": ["tanh", "sigmoid", "relu"],
        "rnn_unit_type": ["lstm", "gru"],
        "input_keep_prob": [1.0],
        "output_keep_prob": [0.95],
        "state_keep_prob": [0.95],
        "variational_recurrent": [true],
        
        "batch_size":[8, 16, 32],
        "sliding_encoder": [18, 24],
        "sliding_decoder": [2, 4],
        
        "layers_units":[[16, 4], [32, 4], [64, 4]],
        "num_epochs": [2000],
        "optimizer":["adam", "rmsprop"],
        "learning_rate": [0.005],
        "patience": [20]
    },
    
    "mlp": {
        "input_dim":[6, 12, 18],
        "dropout_rate": [0.6, 0.8],
        "batch_size":[8, 16, 32, 64],
        "num_epochs":[500],
        "hidden_layers": [[8, 10]],
        "activation": ["relu", "sigmoid", "tanh"],
        "optimizer": ["adam"],
        "patience": [10]
    }

}
